imad213insta/__init__.py
imad213insta/imad.py
imad213insta-213.2.dist-info/METADATA
imad213insta-213.2.dist-info/WHEEL
imad213insta-213.2.dist-info/entry_points.txt
imad213insta-213.2.dist-info/top_level.txt
imad213insta-213.2.dist-info/RECORD
